rinch_sql/__init__.py
rinch_sql/__version__.py
rinch_sql/creator.py
rinch_sql/dataclasses.py
rinch_sql/db_config.py
rinch_sql/mysql.py
rinch_sql/sql.py
rinch_sql/sql_static.py
rinch_sql/table.py
rinch_sql/use_var.py
rinch_sql-10.4.2.dist-info/METADATA
rinch_sql-10.4.2.dist-info/WHEEL
rinch_sql-10.4.2.dist-info/top_level.txt
rinch_sql-10.4.2.dist-info/RECORD
