Metadata-Version: 2.1
Name: rinch_sql
Version: 10.4.2
Summary: a simple orm in python based on [mysql,dataclass].
Author-email: rinch wu <rinch.wu@gmail.com>
License: MIT
Project-URL: Source, https://github.com/rinch-wu/rinch_sql
Project-URL: Homepage, https://github.com/rinch-wu/rinch_sql
Project-URL: Documentation, https://github.com/rinch-wu/rinch_sql
Project-URL: Repository, https://github.com/rinch-wu/rinch_sql
Classifier: Development Status :: 5 - Production/Stable
Classifier: Intended Audience :: Developers
Classifier: Intended Audience :: Education
Classifier: Intended Audience :: Information Technology
Classifier: Intended Audience :: Science/Research
Classifier: License :: OSI Approved :: MIT License
Classifier: Operating System :: OS Independent
Classifier: Programming Language :: Python
Classifier: Programming Language :: Python :: 3.9
Classifier: Programming Language :: Python :: 3.10
Classifier: Programming Language :: Python :: 3.11
Classifier: Programming Language :: Python :: 3.12
Classifier: Programming Language :: Python :: 3.13
Classifier: Topic :: Database
Classifier: Topic :: Software Development
Classifier: Topic :: Software Development :: Libraries :: Application Frameworks
Classifier: Topic :: Software Development :: Libraries :: Python Modules
Requires-Python: >=3.9.0
Requires-Dist: mysql-connector-python
